LiteLogger/__init__.py
LiteLogger/__version__.py
LiteLogger-0.1.1.dist-info/METADATA
LiteLogger-0.1.1.dist-info/WHEEL
LiteLogger-0.1.1.dist-info/top_level.txt
LiteLogger-0.1.1.dist-info/RECORD
