Metadata-Version: 2.1
Name: LiteLogger
Version: 0.1.1
Summary: The official LiteLogger client for Python
Home-page: https://litelogger.com/
Author: Marc Leonard
Author-email: contact@litelogger.com
License: GNU GPLv3
Platform: UNKNOWN
Classifier: License :: OSI Approved :: MIT License
Classifier: Programming Language :: Python
Classifier: Programming Language :: Python :: 3
Classifier: Programming Language :: Python :: 3.6
Classifier: Programming Language :: Python :: Implementation :: CPython
Classifier: Programming Language :: Python :: Implementation :: PyPy
Requires-Python: >=3.7.0
Requires-Dist: requests
